{
	"credit": "Made with Blockbench",
	"textures": {
		"layer0": "item/mojang_fix_it"
	},
	"elements": [
		{
			"from": [0, 0, 0],
			"to": [16, 1, 16],
			"faces": {
				"north": {"uv": [0, 0, 1, 1], "texture": "#layer0"},
				"east": {"uv": [15, 1, 16, 2], "texture": "#layer0"},
				"south": {"uv": [15, 1, 16, 2], "texture": "#layer0"},
				"west": {"uv": [0, 0, 1, 1], "texture": "#layer0"},
				"up": {"uv": [0, 0, 16, 16], "texture": "#layer0"},
				"down": {"uv": [0, 0, 16, 16], "texture": "#layer0"}
			}
		}
	],
	"gui_light": "front",
	"display": {
		"thirdperson_righthand": {
			"rotation": [-180, 0, -180],
			"translation": [-6, 8.25, 3.25]
		},
		"gui": {
			"rotation": [90, 0, 0]
		}
	},
  "overrides": [
    {"predicate": {"custom_model_data":0}, "model":"item/spyglass_modified"},
		{"predicate": {"custom_model_data":1}, "model":"item/aglc"}
	]
}